pythie_serving/__init__.py
pythie_serving/abstract_wrapper.py
pythie_serving/exceptions.py
pythie_serving/lightgbm_wrapper.py
pythie_serving/run.py
pythie_serving/server.py
pythie_serving/sklearn_wrapper.py
pythie_serving/table_wrapper.py
pythie_serving/treelite_wrapper.py
pythie_serving/utils.py
pythie_serving/xgboost_wrapper.py
pythie_serving/tensorflow_proto/__init__.py
pythie_serving/tensorflow_proto/tensorflow/__init__.py
pythie_serving/tensorflow_proto/tensorflow/compiler/__init__.py
pythie_serving/tensorflow_proto/tensorflow/compiler/jit/__init__.py
pythie_serving/tensorflow_proto/tensorflow/compiler/jit/xla_activity_pb2.py
pythie_serving/tensorflow_proto/tensorflow/compiler/jit/xla_activity_pb2_grpc.py
pythie_serving/tensorflow_proto/tensorflow/compiler/jit/xla_compilation_cache_pb2.py
pythie_serving/tensorflow_proto/tensorflow/compiler/jit/xla_compilation_cache_pb2_grpc.py
pythie_serving/tensorflow_proto/tensorflow/compiler/mlir/__init__.py
pythie_serving/tensorflow_proto/tensorflow/compiler/mlir/lite/__init__.py
pythie_serving/tensorflow_proto/tensorflow/compiler/mlir/lite/quantization/__init__.py
pythie_serving/tensorflow_proto/tensorflow/compiler/mlir/lite/quantization/quantization_info_pb2.py
pythie_serving/tensorflow_proto/tensorflow/compiler/mlir/lite/quantization/quantization_info_pb2_grpc.py
pythie_serving/tensorflow_proto/tensorflow/compiler/mlir/quantization/__init__.py
pythie_serving/tensorflow_proto/tensorflow/compiler/mlir/quantization/tensorflow/__init__.py
pythie_serving/tensorflow_proto/tensorflow/compiler/mlir/quantization/tensorflow/quantization_options_pb2.py
pythie_serving/tensorflow_proto/tensorflow/compiler/mlir/quantization/tensorflow/quantization_options_pb2_grpc.py
pythie_serving/tensorflow_proto/tensorflow/compiler/mlir/tfrt/__init__.py
pythie_serving/tensorflow_proto/tensorflow/compiler/mlir/tfrt/analysis/__init__.py
pythie_serving/tensorflow_proto/tensorflow/compiler/mlir/tfrt/analysis/analysis_pb2.py
pythie_serving-3.4.3.dist-info/LICENSE
pythie_serving-3.4.3.dist-info/METADATA
pythie_serving-3.4.3.dist-info/WHEEL
pythie_serving-3.4.3.dist-info/entry_points.txt
pythie_serving-3.4.3.dist-info/top_level.txt
pythie_serving-3.4.3.dist-info/zip-safe
pythie_serving-3.4.3.dist-info/RECORD
