Metadata-Version: 2.1
Name: pythie-serving
Version: 3.4.3
Summary: A GRPC server to serve model types using tensorflow-serving .proto services
Home-page: https://gitlab.cayzn.com/wiremind/data-science/pythie-neos.git
Author: wiremind data science team
Author-email: data-science@wiremind.io
License: UNKNOWN
Platform: UNKNOWN
Classifier: Programming Language :: Python :: 3.11
Classifier: Programming Language :: Python :: 3 :: Only
Classifier: License :: OSI Approved :: GNU Lesser General Public License v3 or later (LGPLv3+)
Requires-Python: >=3.11
Requires-Dist: numpy ~=1.23.0
Requires-Dist: grpcio ~=1.51
Requires-Dist: protobuf ~=4.22
Provides-Extra: all
Requires-Dist: lightgbm ~=3.3.2 ; extra == 'all'
Requires-Dist: xgboost ~=0.90 ; extra == 'all'
Requires-Dist: treelite-runtime ~=2.2.2 ; extra == 'all'
Requires-Dist: scikit-learn ~=1.2.0 ; extra == 'all'
Requires-Dist: cloudpickle ~=2.1.0 ; extra == 'all'
Requires-Dist: pytest ~=6.2 ; extra == 'all'
Requires-Dist: black ~=22.6.0 ; extra == 'all'
Requires-Dist: isort ~=5.10.1 ; extra == 'all'
Requires-Dist: flake8 ~=4.0.1 ; extra == 'all'
Requires-Dist: flake8-mutable ~=1.2.0 ; extra == 'all'
Requires-Dist: mypy ==0.991 ; extra == 'all'
Requires-Dist: mypy-protobuf ~=3.4.0 ; extra == 'all'
Requires-Dist: types-protobuf ; extra == 'all'
Requires-Dist: pyupgrade ~=3.3.1 ; extra == 'all'
Requires-Dist: treelite ~=2.4 ; extra == 'all'
Requires-Dist: pre-commit ~=2.20.0 ; extra == 'all'
Requires-Dist: pip-tools ~=6.12.3 ; extra == 'all'
Provides-Extra: dev
Requires-Dist: lightgbm ~=3.3.2 ; extra == 'dev'
Requires-Dist: xgboost ~=0.90 ; extra == 'dev'
Requires-Dist: treelite-runtime ~=2.2.2 ; extra == 'dev'
Requires-Dist: scikit-learn ~=1.2.0 ; extra == 'dev'
Requires-Dist: cloudpickle ~=2.1.0 ; extra == 'dev'
Requires-Dist: pytest ~=6.2 ; extra == 'dev'
Requires-Dist: black ~=22.6.0 ; extra == 'dev'
Requires-Dist: isort ~=5.10.1 ; extra == 'dev'
Requires-Dist: flake8 ~=4.0.1 ; extra == 'dev'
Requires-Dist: flake8-mutable ~=1.2.0 ; extra == 'dev'
Requires-Dist: mypy ==0.991 ; extra == 'dev'
Requires-Dist: mypy-protobuf ~=3.4.0 ; extra == 'dev'
Requires-Dist: types-protobuf ; extra == 'dev'
Requires-Dist: pyupgrade ~=3.3.1 ; extra == 'dev'
Requires-Dist: treelite ~=2.4 ; extra == 'dev'
Requires-Dist: pre-commit ~=2.20.0 ; extra == 'dev'
Requires-Dist: pip-tools ~=6.12.3 ; extra == 'dev'
Provides-Extra: serving
Requires-Dist: lightgbm ~=3.3.2 ; extra == 'serving'
Requires-Dist: xgboost ~=0.90 ; extra == 'serving'
Requires-Dist: treelite-runtime ~=2.2.2 ; extra == 'serving'
Requires-Dist: scikit-learn ~=1.2.0 ; extra == 'serving'
Requires-Dist: cloudpickle ~=2.1.0 ; extra == 'serving'
Provides-Extra: test
Requires-Dist: lightgbm ~=3.3.2 ; extra == 'test'
Requires-Dist: xgboost ~=0.90 ; extra == 'test'
Requires-Dist: treelite-runtime ~=2.2.2 ; extra == 'test'
Requires-Dist: scikit-learn ~=1.2.0 ; extra == 'test'
Requires-Dist: cloudpickle ~=2.1.0 ; extra == 'test'
Requires-Dist: pytest ~=6.2 ; extra == 'test'
Requires-Dist: black ~=22.6.0 ; extra == 'test'
Requires-Dist: isort ~=5.10.1 ; extra == 'test'
Requires-Dist: flake8 ~=4.0.1 ; extra == 'test'
Requires-Dist: flake8-mutable ~=1.2.0 ; extra == 'test'
Requires-Dist: mypy ==0.991 ; extra == 'test'
Requires-Dist: mypy-protobuf ~=3.4.0 ; extra == 'test'
Requires-Dist: types-protobuf ; extra == 'test'
Requires-Dist: pyupgrade ~=3.3.1 ; extra == 'test'
